appoptics_apm-5.2.0.dist-info/top_level.txt
appoptics_apm-5.2.0.dist-info/WHEEL
appoptics_apm-5.2.0.dist-info/LICENSE
appoptics_apm-5.2.0.dist-info/METADATA
appoptics_apm-5.2.0.dist-info/NOTICE
appoptics_apm-5.2.0.dist-info/RECORD
appoptics_apm.libs/libz-745e0a09.so.1.2.7
appoptics_apm/appoptics_apm_noop.py
appoptics_apm/transaction_filter.py
appoptics_apm/inst_httplib.py
appoptics_apm/util.py
appoptics_apm/version.py
appoptics_apm/inst_logging.py
appoptics_apm/json_encoder.py
appoptics_apm/__init__.py
appoptics_apm/aoasync.py
appoptics_apm/inst_pymongo.py
appoptics_apm/aws_lambda_wrapper.py
appoptics_apm/inst_redis.py
appoptics_apm/loader.py
appoptics_apm/inst_django_templates.py
appoptics_apm/ao_logging.py
appoptics_apm/tornado_oboe.py
appoptics_apm/skeleton.py
appoptics_apm/inst_django_orm.py
appoptics_apm/djangoware.py
appoptics_apm/inst_sqlalchemy.py
appoptics_apm/middleware.py
appoptics_apm/inst_memcache.py
appoptics_apm/swig/liboboe-1.0.so.0
appoptics_apm/swig/_oboe.cpython-39-x86_64-linux-gnu.so
appoptics_apm/swig/__init__.py
appoptics_apm/swig/VERSION
appoptics_apm/swig/oboe.py
appoptics_apm/swig/bson/bson.h
appoptics_apm/swig/bson/platform_hacks.h
