Metadata-Version: 2.1
Name: appoptics-apm
Version: 5.2.0
Summary: AppOptics APM libraries, instrumentation, and web middleware components for WSGI, Django, and Tornado.
Home-page: https://www.appoptics.com/monitor/python-performance
Author: SolarWinds, LLC
Author-email: support@appoptics.com
License: LICENSE
Download-URL: https://pypi.python.org/pypi/appoptics_apm
Keywords: appoptics_apm traceview tracelytics oboe liboboe instrumentation performance wsgi middleware django
Platform: UNKNOWN
Classifier: Programming Language :: Python :: 3.5
Classifier: Programming Language :: Python :: 3.6
Classifier: Programming Language :: Python :: 3.7
Classifier: Programming Language :: Python :: 3.8
Classifier: Programming Language :: Python :: 3.9
Requires-Python: >=3.5
License-File: LICENSE
License-File: NOTICE
